MANIFEST.in
README.rst
setup.py
eventlog/__init__.py
eventlog/admin.py
eventlog/mixins.py
eventlog/models.py
eventlog/signals.py
eventlog/stats.py
eventlog.egg-info/PKG-INFO
eventlog.egg-info/SOURCES.txt
eventlog.egg-info/dependency_links.txt
eventlog.egg-info/not-zip-safe
eventlog.egg-info/requires.txt
eventlog.egg-info/top_level.txt