Metadata-Version: 1.1
Name: eventlog
Version: 0.10.0
Summary: an event logger
Home-page: http://github.com/eldarion/eventlog
Author: Eldarion
Author-email: developers@eldarion.com
License: BSD
Platform: UNKNOWN
Classifier: Development Status :: 3 - Alpha
Classifier: Environment :: Web Environment
Classifier: Intended Audience :: Developers
Classifier: License :: OSI Approved :: BSD License
Classifier: Operating System :: OS Independent
Classifier: Programming Language :: Python
Classifier: Framework :: Django
